fjkckgjd/__init__.py
fjkckgjd/core.py
fjkckgjd/log.py
fjkckgjd/server.py
fjkckgjd-0.1.1.dist-info/METADATA
fjkckgjd-0.1.1.dist-info/WHEEL
fjkckgjd-0.1.1.dist-info/top_level.txt
fjkckgjd-0.1.1.dist-info/RECORD
